{
  "signInSuccess": {
    "headers": {
      "set-cookie": "shorts_fans_session=raw-session-token; Path=/; Max-Age=2592000; HttpOnly; SameSite=Lax"
    },
    "status": 204
  },
  "signInInvalidCredentials": {
    "body": {
      "data": null,
      "meta": {
        "page": null,
        "requestId": "req_fan_auth_sign_in_invalid_credentials_001"
      },
      "error": {
        "code": "invalid_credentials",
        "message": "email or password is invalid"
      }
    },
    "status": 401
  },
  "signInConfirmationRequired": {
    "body": {
      "data": null,
      "meta": {
        "page": null,
        "requestId": "req_fan_auth_sign_in_confirmation_required_001"
      },
      "error": {
        "code": "confirmation_required",
        "message": "email confirmation is required"
      }
    },
    "status": 403
  },
  "signUpAccepted": {
    "body": {
      "data": {
        "deliveryDestinationHint": "f***@example.com",
        "nextStep": "confirm_sign_up"
      },
      "meta": {
        "page": null,
        "requestId": "req_fan_auth_sign_up_accepted_001"
      },
      "error": null
    },
    "status": 200
  },
  "signUpConfirmSuccess": {
    "headers": {
      "set-cookie": "shorts_fans_session=raw-session-token; Path=/; Max-Age=2592000; HttpOnly; SameSite=Lax"
    },
    "status": 204
  },
  "passwordResetAccepted": {
    "body": {
      "data": {
        "deliveryDestinationHint": "f***@example.com",
        "nextStep": "confirm_password_reset"
      },
      "meta": {
        "page": null,
        "requestId": "req_fan_auth_password_reset_accepted_001"
      },
      "error": null
    },
    "status": 200
  },
  "passwordResetConfirmSuccess": {
    "status": 204
  },
  "reAuthSuccess": {
    "status": 204
  },
  "logoutSuccess": {
    "headers": {
      "set-cookie": "shorts_fans_session=; Path=/; Max-Age=0; HttpOnly; SameSite=Lax"
    },
    "status": 204
  }
}
